scRL/ActorCriticCore.py
scRL/DDQNCore.py
scRL/EnvironmentCore.py
scRL/GridCore.py
scRL/TabularQCore.py
scRL/Trainer.py
scRL/__init__.py
scRL/utils.py
scRL/Simulator/Core.py
scRL/Simulator/Results.py
scRL/Simulator/__init__.py
scRL/Trajectory/Core.py
scRL/Trajectory/Results.py
scRL/Trajectory/__init__.py
singlecellRL-0.4.0.dist-info/LICENSE
singlecellRL-0.4.0.dist-info/METADATA
singlecellRL-0.4.0.dist-info/WHEEL
singlecellRL-0.4.0.dist-info/top_level.txt
singlecellRL-0.4.0.dist-info/RECORD
