Metadata-Version: 2.1
Name: singlecellRL
Version: 0.4.0
Summary: single cell reinforcement learning
Home-page: https://github.com/PeterPonyu/scRL
Author: Zeyu Fu
Author-email: 1119692089@qq.com
License: MIT
Platform: UNKNOWN
Classifier: License :: OSI Approved :: MIT License
Classifier: Development Status :: 4 - Beta
Classifier: Programming Language :: Python :: 3
Classifier: Intended Audience :: Science/Research
Classifier: Topic :: Scientific/Engineering :: Bio-Informatics
Requires-Python: >=3.9
License-File: LICENSE
Requires-Dist: anndata >=0.8.0
Requires-Dist: numpy >=1.23.5
Requires-Dist: pandas >=1.5.2
Requires-Dist: scikit-learn >=1.2.1
Requires-Dist: torch >=1.13.1
Requires-Dist: networkx >=2.8.8
Requires-Dist: matplotlib >=3.6.3
Requires-Dist: seaborn >=0.11.2
Requires-Dist: joblib >=1.2.0
Requires-Dist: tqdm >=4.64.1
Requires-Dist: pygam >=0.8.0
